{
  "sessionId": "default",
  "state": "authenticated",
  "reauthRequired": false,
  "clientId": null,
  "token": {
    "accessTokenPresent": true,
    "tokenType": "Bearer",
    "expiresAt": null,
    "scopes": [
      "mcp:tools"
    ],
    "issuedAt": "2026-05-29T11:55:24.339709+00:00",
    "lastValidatedAt": "2026-05-29T11:55:24.339709+00:00"
  },
  "domains": {
    "food": true,
    "instamart": true,
    "dineout": true
  },
  "lastAuthError": null,
  "authFreshUntil": null,
  "userSessionExpiresAt": "2026-06-28T11:55:24.339816+00:00",
  "devMode": true,
  "createdAt": "2026-05-29T11:55:24.339709+00:00",
  "updatedAt": "2026-05-29T11:55:24.340497+00:00"
}